adsb_track/__init__.py
adsb_track/aircraft.py
adsb_track/analyze.py
adsb_track/const.py
adsb_track/record.py
adsb_track/replay.py
adsb_track/stream.py
adsb_track/database/__init__.py
adsb_track/database/interface.py
adsb_track/database/schema.py
adsb_track-0.2.0.dist-info/LICENSE
adsb_track-0.2.0.dist-info/METADATA
adsb_track-0.2.0.dist-info/WHEEL
adsb_track-0.2.0.dist-info/top_level.txt
adsb_track-0.2.0.dist-info/RECORD
