Metadata-Version: 2.1
Name: adsb-track
Version: 0.2.0
Summary: ADS-B message recorder
Home-page: https://github.com/xander-hirsch/adsb-track
Author: Xander Hirsch
Author-email: x.hirsch@icloud.com
License: MIT
Platform: UNKNOWN
Classifier: Programming Language :: Python :: 3
Classifier: License :: OSI Approved :: MIT License
Classifier: Operating System :: OS Independent
Requires-Python: >=3.7
License-File: LICENSE
Requires-Dist: dash
Requires-Dist: pyModeS
Requires-Dist: pandas
Requires-Dist: SQLAlchemy
